CHANGES
LICENSE
MANIFEST.in
README
setup.py
tox.ini
django_auth_ldap/__init__.py
django_auth_ldap/backend.py
django_auth_ldap/config.py
django_auth_ldap/dn.py
django_auth_ldap/models.py
django_auth_ldap/tests.py
django_auth_ldap_ng.egg-info/PKG-INFO
django_auth_ldap_ng.egg-info/SOURCES.txt
django_auth_ldap_ng.egg-info/dependency_links.txt
django_auth_ldap_ng.egg-info/pbr.json
django_auth_ldap_ng.egg-info/requires.txt
django_auth_ldap_ng.egg-info/top_level.txt
docs/Makefile
docs/_templates/globaltoc.html
docs/archive/versions/1.0.19/.buildinfo
docs/archive/versions/1.0.19/genindex.html
docs/archive/versions/1.0.19/index.html
docs/archive/versions/1.0.19/objects.inv
docs/archive/versions/1.0.19/py-modindex.html
docs/archive/versions/1.0.19/search.html
docs/archive/versions/1.0.19/searchindex.js
docs/archive/versions/1.0.19/_sources/index.txt
docs/archive/versions/1.0.19/_static/ajax-loader.gif
docs/archive/versions/1.0.19/_static/basic.css
docs/archive/versions/1.0.19/_static/comment-bright.png
docs/archive/versions/1.0.19/_static/comment-close.png
docs/archive/versions/1.0.19/_static/comment.png
docs/archive/versions/1.0.19/_static/default.css
docs/archive/versions/1.0.19/_static/doctools.js
docs/archive/versions/1.0.19/_static/down-pressed.png
docs/archive/versions/1.0.19/_static/down.png
docs/archive/versions/1.0.19/_static/file.png
docs/archive/versions/1.0.19/_static/jquery.js
docs/archive/versions/1.0.19/_static/minus.png
docs/archive/versions/1.0.19/_static/plus.png
docs/archive/versions/1.0.19/_static/pygments.css
docs/archive/versions/1.0.19/_static/searchtools.js
docs/archive/versions/1.0.19/_static/sidebar.js
docs/archive/versions/1.0.19/_static/underscore.js
docs/archive/versions/1.0.19/_static/up-pressed.png
docs/archive/versions/1.0.19/_static/up.png
docs/archive/versions/1.0.19/_static/websupport.js
docs/ext/daldocs.py
docs/source/.spell.utf-8.add
docs/source/.spell.utf-8.add.spl
docs/source/authentication.rst
docs/source/changes.rst
docs/source/conf.py
docs/source/example.rst
docs/source/groups.rst
docs/source/index.rst
docs/source/install.rst
docs/source/logging.rst
docs/source/multiconfig.rst
docs/source/performance.rst
docs/source/permissions.rst
docs/source/reference.rst
docs/source/users.rst
